function/__init__.py
function/test_t.py
timelinetestpack-1.1.dist-info/METADATA
timelinetestpack-1.1.dist-info/WHEEL
timelinetestpack-1.1.dist-info/top_level.txt
timelinetestpack-1.1.dist-info/RECORD
