Metadata-Version: 2.1
Name: timelinetestpack
Version: 1.1
Summary: This is timelinetestpack.
Home-page: https://github.com/F-Jirayut/create_p
Author: U test
Author-email: fayristh0268@gmail.com
License: MIT
Platform: UNKNOWN
Requires-Python: >=3.6
